hostswitcher.py
hostswitcher/__init__.py
hostswitcher/__main__.py
hostswitcher/version.py
hostswitcher/cli/__init__.py
hostswitcher/cli/commands/__init__.py
hostswitcher/cli/commands/combine.py
hostswitcher/cli/commands/create.py
hostswitcher/cli/commands/edit.py
hostswitcher/cli/commands/init.py
hostswitcher/cli/commands/ls.py
hostswitcher/cli/commands/remove.py
hostswitcher/cli/commands/set.py
hostswitcher/cli/commands/show.py
hostswitcher/lib/__init__.py
hostswitcher/lib/table.py
hostswitcher/utils/__init__.py
hostswitcher/utils/file.py
hostswitcher/utils/logger.py
hostswitcher/utils/text.py
hostswitcher-0.0.1a6.dist-info/DESCRIPTION.rst
hostswitcher-0.0.1a6.dist-info/METADATA
hostswitcher-0.0.1a6.dist-info/RECORD
hostswitcher-0.0.1a6.dist-info/WHEEL
hostswitcher-0.0.1a6.dist-info/entry_points.txt
hostswitcher-0.0.1a6.dist-info/metadata.json
hostswitcher-0.0.1a6.dist-info/top_level.txt
