Metadata-Version: 2.0
Name: hostswitcher
Version: 0.0.1a6
Summary: Multiplatform hosts file manager
Home-page: https://github.com/riccardocurcio/hostswitcher
Author: Riccardo Curcio, Angelo Landino, Giuseppe Iannelli
Author-email: curcioriccardo@gmail.com,angelolandino@hotmail.it,me@giuseppeiannelli.it
License: UNKNOWN
Platform: UNKNOWN
Classifier: Development Status :: 3 - Alpha
Classifier: Environment :: Console
Classifier: Intended Audience :: System Administrators
Classifier: Intended Audience :: Developers
Classifier: License :: OSI Approved :: GNU General Public License (GPL)
Classifier: Programming Language :: Python :: 3
Classifier: Operating System :: OS Independent
Requires-Python: >=3
Requires-Dist: termcolor
Requires-Dist: colorama
